{
    "planetData": {
        "Mercury": {
            "a": 0.3870,
            "b": 0.3787,
            "c": 0.0796,
            "e": 0.2056,
            "rotationSpeedAroundSun": 1.607,
            "eulerDistanceFromSun": 2.0790e+3,
            "scaleFactor": 17,
            "tiltAxisZ": 0.03,
            "planetSize": 0.3829,
            "orbitalSpeed": 1.607,
            "gravitationalPull": 3.7,
            "cosmicObjectDistanceX": 1,
            "cosmicObjectDistanceZ": 1,
            "cosmicObjectSpeed": 3,
            "cosmicObjectScaleFactor": 1,
            "mass": "0.330 × 10^24 kg",
            "diameter": "4 879",
            "perimeter": "15 329",
            "rotationSpeed": 47.4,
            "rotationPeriod": "1 407.6",
            "orbitalPeriod": 88,
            "perihelion": "46 x 10^6 km",
            "aphelion": "69.8 x 10^6 km"
        },
        "Venus": {
            "a": 0.7230,
            "b": 0.72298,
            "c": 0.0049,
            "e": 0.0068,
            "rotationSpeedAroundSun": 1.174,
            "eulerDistanceFromSun": 3.8849e+3,
            "scaleFactor": 14,
            "tiltAxisZ": 177.4,
            "planetSize": 0.9499,
            "orbitalSpeed": 1.174,
            "gravitationalPull": 8.87,
            "cosmicObjectDistanceX": 1,
            "cosmicObjectDistanceZ": 1,
            "cosmicObjectSpeed": 3,
            "cosmicObjectScaleFactor": 1.8,
            "mass": "4.87 × 10^24 kg",
            "diameter": "12 104",
            "perimeter": "38 025",
            "rotationSpeed": 35.0,
            "rotationPeriod": "-5 832.5",
            "orbitalPeriod": 224.7,
            "perihelion": "107.5 x 10^6 km",
            "aphelion": "108.9 x 10^6 km"
        },
        "Earth": {
            "a": 1.0000,
            "b": 0.99986,
            "c": 0.0167,
            "e": 0.0167,
            "rotationSpeedAroundSun": 1.000,
            "eulerDistanceFromSun": 5.3709e+3,
            "scaleFactor": 14,
            "tiltAxisZ": 23.4,
            "planetSize": 1,
            "orbitalSpeed": 1.000,
            "gravitationalPull": 9.807,
            "cosmicObjectDistanceX": 1,
            "cosmicObjectDistanceZ": 1,
            "cosmicObjectSpeed": 3,
            "cosmicObjectScaleFactor": 2,
            "mass": "5.97 × 10^24 kg",
            "diameter": "12 756",
            "perimeter": "40 075",
            "rotationSpeed": 29.8,
            "rotationPeriod": 23.9,
            "orbitalPeriod": 365.2,
            "perihelion": "147.1 x 10^6 km",
            "aphelion": "152.1 x 10^6 km"
        },
        "Mars": {
            "a": 1.5240,
            "b": 1.5174,
            "c": 0.1424,
            "e": 0.0934,
            "rotationSpeedAroundSun": 0.802,
            "eulerDistanceFromSun": 8.1834e+3,
            "scaleFactor": 13,
            "tiltAxisZ": 25.2,
            "planetSize": 0.5320,
            "orbitalSpeed": 0.802,
            "gravitationalPull": 3.711,
            "cosmicObjectDistanceX": 1,
            "cosmicObjectDistanceZ": 1,
            "cosmicObjectSpeed": 3,
            "cosmicObjectScaleFactor": 1.8,
            "mass": "0.642 × 10^24 kg",
            "diameter": "6 792",
            "perimeter": "21 344",
            "rotationSpeed": 24.1,
            "rotationPeriod": 24.6,
            "orbitalPeriod": 687,
            "perihelion": "206.6 x 10^6 km",
            "aphelion": "249.2 x 10^6 km"
        },
        "Jupiter": {
            "a": 5.2044,
            "b": 5.1982,
            "c": 0.2520,
            "e": 0.0484,
            "rotationSpeedAroundSun": 0.434,
            "eulerDistanceFromSun": 2.7951e+4,
            "scaleFactor": 5.5,
            "tiltAxisZ": 3.1,
            "planetSize": 2.194,
            "orbitalSpeed": 0.434,
            "gravitationalPull": 24.79,
            "cosmicObjectDistanceX": 1,
            "cosmicObjectDistanceZ": 1,
            "cosmicObjectSpeed": 3,
            "cosmicObjectScaleFactor": 3,
            "mass": "1898 × 10^24 kg",
            "diameter": "142 984",
            "perimeter": "439 264",
            "rotationSpeed": 13.1,
            "rotationPeriod": 9.9,
            "orbitalPeriod": 4331,
            "perihelion": "740.5 x 10^6 km",
            "aphelion": "816.6 x 10^6 km"
        },
        "Saturn": {
            "a": 9.5826,
            "b": 9.5673,
            "c": 0.5181,
            "e": 0.0542,
            "rotationSpeedAroundSun": 0.323,
            "eulerDistanceFromSun": 5.1464e+4,
            "scaleFactor": 4.2,
            "tiltAxisZ": 26.7,
            "planetSize": 1.828,
            "orbitalSpeed": 0.323,
            "gravitationalPull": 10.44,
            "cosmicObjectDistanceX": 1,
            "cosmicObjectDistanceZ": 1,
            "cosmicObjectSpeed": 3,
            "cosmicObjectScaleFactor": 2.5,
            "mass": "568 × 10^24 kg",
            "diameter": "120 536",
            "perimeter": "378 675",
            "rotationSpeed": 9.7,
            "rotationPeriod": 10.7,
            "orbitalPeriod": "10 747",
            "perihelion": "1 352.6 x 10^6 km",
            "aphelion": "1 514.5 x 10^6 km"
        },
        "Uranus": {
            "a": 19.1848,
            "b": 19.1645,
            "c": 0.9055,
            "e": 0.0472,
            "rotationSpeedAroundSun": 0.228,
            "eulerDistanceFromSun": 1.0328e+5,
            "scaleFactor": 2.6,
            "tiltAxisZ": 97.8,
            "planetSize": 0.7962,
            "orbitalSpeed": 0.228,
            "gravitationalPull": 8.87,
            "cosmicObjectDistanceX": 1,
            "cosmicObjectDistanceZ": 1,
            "cosmicObjectSpeed": 3,
            "cosmicObjectScaleFactor": 2.2,
            "mass": "86.8 × 10^24 kg",
            "diameter": "51 118",
            "perimeter": "160 590",
            "rotationSpeed": 6.8,
            "rotationPeriod": -17.2,
            "orbitalPeriod": "30 589",
            "perihelion": "2 741.3 x 10^6 km",
            "aphelion": "3 003.6 x 10^6 km"
        },
        "Neptune": {
            "a": 30.110,
            "b": 30.1087,
            "c": 0.2587,
            "e": 0.0086,
            "rotationSpeedAroundSun": 0.182,
            "eulerDistanceFromSun": 1.6168e+5,
            "scaleFactor": 2,
            "tiltAxisZ": 28.3,
            "planetSize": 0.773,
            "orbitalSpeed": 0.128,
            "gravitationalPull": 11.15,
            "cosmicObjectDistanceX": 1,
            "cosmicObjectDistanceZ": 1,
            "cosmicObjectSpeed": 3,
            "cosmicObjectScaleFactor": 2,
            "mass": "102 × 10^24 kg",
            "diameter": "49 528",
            "perimeter": "155 600",
            "rotationSpeed": 5.4,
            "rotationPeriod": 16.1,
            "orbitalPeriod": "59 800",
            "perihelion": "4 444.5 x 10^6 km",
            "aphelion": "4 545.7 x 10^6 km"
        }
    },
    "moonData": {
        "Moon": {
            "a": 1,
            "b": 1,
            "c": 0.04,
            "scaleFactor": 2,
            "planet": "Earth",
            "mass": "7.3477 x 10^22 kg",
            "diameter": "1 737.1",
            "orbitalSpeed": 1.022,
            "orbitalPeriod": 27.3216,
            "distanceFromPlanet": "384 399",
            "minTemperature": "-173 °C",
            "maxTemperature": "116 °C"
        },
        "Io": {
            "a": 1.0968,
            "b": 1.0120,
            "c": 0.06,
            "scaleFactor": 2.2,
            "planet": "Jupiter",
            "mass": "8.94 x 10^22 kg",
            "diameter": "41.910",
            "orbitalSpeed": 17.34,
            "orbitalPeriod": 1.7691,
            "distanceFromPlanet": "421 600",
            "minTemperature": "-183 °C",
            "maxTemperature": "-143 °C"
        },
        "Europa": {
            "a": 1.7453,
            "b": 1.7527,
            "c": 0.06,
            "scaleFactor": 1.8,
            "planet": "Jupiter",
            "mass": "4.7998 × 10^22 kg",
            "diameter": "1 560.8",
            "orbitalSpeed": 13.740,
            "orbitalPeriod": 3.5512,
            "distanceFromPlanet": "421 600",
            "minTemperature": "-223 °C",
            "maxTemperature": "-148 °C"
        },
        "Ganymede": {
            "a": 2.7846,
            "b": 2.6264,
            "c": 0.08,
            "scaleFactor": 1.5,
            "planet": "Jupiter",
            "mass": "14.819 × 10^22 kg",
            "diameter": "2 634.1",
            "orbitalSpeed": 10.880,
            "orbitalPeriod": 7.1546,
            "distanceFromPlanet": "1 070 400",
            "minTemperature": "-203 °C",
            "maxTemperature": "-121 °C"
        },
        "Callisto": {
            "a": 4.8978,
            "b": 5.0110,
            "c": 0.02,
            "scaleFactor": 1,
            "planet": "Jupiter",
            "mass": "10.758 × 10^22 kg",
            "diameter": "2 410.3",
            "orbitalSpeed": 8.204,
            "orbitalPeriod": 16.6890,
            "distanceFromPlanet": "1 882 700",
            "minTemperature": "-193 °C",
            "maxTemperature": "-108 °C"
        },
        "Rhea": {
            "a": 1.3713,
            "b": 1.3613,
            "c": 0.02,
            "scaleFactor": 1.8,
            "planet": "Saturn",
            "mass": "0.2306 × 10^22 kg",
            "diameter": "764.3",
            "orbitalSpeed": 8.48,
            "orbitalPeriod": 4.5182,
            "distanceFromPlanet": "527 108",
            "minTemperature": "-220 °C",
            "maxTemperature": "-174 °C"
        },
        "Titan": {
            "a": 3.1787,
            "b": 3.0987,
            "c": 0.01,
            "scaleFactor": 1.2,
            "planet": "Saturn",
            "mass": "13.452 × 10^22 kg",
            "diameter": "2 576",
            "orbitalSpeed": 5.57,
            "orbitalPeriod": 15.945,
            "distanceFromPlanet": "1 221 870",
            "minTemperature": "−179.5 °C",
            "maxTemperature": "−179.5 °C"
        },
        "Ariel": {
            "a": 0.4966,
            "b": 0.5065,
            "c": 0.01,
            "scaleFactor": 3,
            "planet": "Uranus",
            "mass": "0.135 × 10^22 kg",
            "diameter": "578.9",
            "orbitalSpeed": 5.509,
            "orbitalPeriod": 2.520,
            "distanceFromPlanet": "190 900",
            "minTemperature": "? °C",
            "maxTemperature": "−189 °C"
        },
        "Umbriel": {
            "a": 0.6920,
            "b": 0.6780,
            "c": 0.01,
            "scaleFactor": 3,
            "planet": "Uranus",
            "mass": "0.12 × 10^22 kg",
            "diameter": "584.7",
            "orbitalSpeed": 4.668,
            "orbitalPeriod": 4.144,
            "distanceFromPlanet": "266 000",
            "minTemperature": "? °C",
            "maxTemperature": "−188 °C"
        },
        "Titania": {
            "a": 1.1350,
            "b": 1.1278,
            "c": 0.03,
            "scaleFactor": 2.2,
            "planet": "Uranus",
            "mass": "0.35 × 10^22 kg",
            "diameter": "788.9",
            "orbitalSpeed": 3.644,
            "orbitalPeriod": 8.706,
            "distanceFromPlanet": "436 300",
            "minTemperature": "-213 °C",
            "maxTemperature": "−184 °C"
        },
        "Oberon": {
            "a": 1.5180,
            "b": 1.5012,
            "c": 0.02,
            "scaleFactor": 2,
            "planet": "Uranus",
            "mass": "0.3014 × 10^22 kg",
            "diameter": "761.4",
            "orbitalSpeed": 3.152,
            "orbitalPeriod": 13.46,
            "distanceFromPlanet": "583 519",
            "minTemperature": "-203 °C",
            "maxTemperature": "−193 °C"
        },
        "Triton": {
            "a": 0.9229,
            "b": 0.8815,
            "c": 0.02,
            "scaleFactor": 2,
            "planet": "Neptune",
            "mass": "2.14 × 10^22 kg",
            "diameter": "1 353.4",
            "orbitalSpeed": 4.39,
            "orbitalPeriod": 5.877,
            "distanceFromPlanet": "354 759",
            "minTemperature": "−235.2 °C",
            "maxTemperature": "−235.2 °C"
        }
    }
}